{
  "commands": [],
  "prefix": "!",
  "mention": false,
  "services": {
    "DiscordService": {
      "auth": ""
    }
  },
  "managers": {
    "ListManager": {
      "prefix": "list",
      "commands": [
        {
          "command": "managers",
          "event": "managers"
        },
        {
          "command": "services",
          "event": "services"
        },
        {
          "command": "commands",
          "event": "commands"
        }
      ]
    },
    "DisnodeManager": {
      "prefix": "disnode",
      "commands": [
        {
          "command": "disconnect",
          "event": "disconnect"
        },
        {
          "command": "connect",
          "event": "connect"
        },
        {
          "command": "info",
          "event": "info"
        }
      ]
    }
  }
}
